plain/oauth/CHANGELOG.md
plain/oauth/README.md
plain/oauth/__init__.py
plain/oauth/admin.py
plain/oauth/config.py
plain/oauth/default_settings.py
plain/oauth/exceptions.py
plain/oauth/models.py
plain/oauth/preflight.py
plain/oauth/providers.py
plain/oauth/urls.py
plain/oauth/views.py
plain/oauth/migrations/0001_initial.py
plain/oauth/migrations/__init__.py
plain/oauth/templates/oauth/callback.html
plain_oauth-0.39.0.dist-info/METADATA
plain_oauth-0.39.0.dist-info/WHEEL
plain_oauth-0.39.0.dist-info/licenses/LICENSE
plain_oauth-0.39.0.dist-info/RECORD
