Metadata-Version: 2.4
Name: plain.oauth
Version: 0.39.0
Summary: Let users log in with OAuth providers.
Author-email: Dave Gaeddert <dave.gaeddert@dropseed.dev>
License-Expression: BSD-3-Clause
License-File: LICENSE
Requires-Python: >=3.13
Requires-Dist: plain-auth<1.0.0
Requires-Dist: plain-models<1.0.0
Requires-Dist: plain<1.0.0
Requires-Dist: requests>=2.0.0
